README.md
setup.py
mini_color/__init__.py
mini_color/color.py
mini_color/exception.py
mini_color.egg-info/PKG-INFO
mini_color.egg-info/SOURCES.txt
mini_color.egg-info/dependency_links.txt
mini_color.egg-info/top_level.txt