Metadata-Version: 2.1
Name: mini-color
Version: 0.1.0
Summary: mini_color
Home-page: https://github.com/Kaguya233qwq/MiniColor
Author: Kaguya233qwq
Author-email: 1435608435@qq.com
License: UNKNOWN
Keywords: colored-text,library,彩色文本
Platform: any
Classifier: Programming Language :: Python :: 3
Classifier: License :: OSI Approved :: GNU General Public License v3 (GPLv3)
Classifier: Natural Language :: Chinese (Simplified)
